chronos/__init__.py
chronos/chronos.py
chronos/extinction.py
chronos/isochrone.py
chronos/leastsquares.py
chronos/utils.py
chronos/data/extinctions.txt
chronos/data/parsec_grid.fits.gz
chronos/data/parsec_grid_old.fits.gz
thechronos-1.0.17.dist-info/licenses/LICENSE
thechronos-1.0.17.dist-info/METADATA
thechronos-1.0.17.dist-info/WHEEL
thechronos-1.0.17.dist-info/top_level.txt
thechronos-1.0.17.dist-info/RECORD
