Metadata-Version: 2.4
Name: thechronos
Version: 1.0.17
Summary: Automatic isochrone fitting to photometric data
Home-page: https://github.com/dnidever/chronos
Author: David Nidever
Author-email: dnidever@montana.edu
License: MIT
Requires: numpy
Requires: astropy(>=4.0)
Requires: scipy
Requires: dlnpyutils
Requires: emcee
Requires: cornner
Requires-Python: >=3.6
License-File: LICENSE
Requires-Dist: numpy
Requires-Dist: astropy
Requires-Dist: scipy
Requires-Dist: dlnpyutils
Requires-Dist: emcee
Requires-Dist: corner
Provides-Extra: test
Requires-Dist: pytest; extra == "test"
Requires-Dist: pytest-astropy; extra == "test"
Requires-Dist: ipython; extra == "test"
Provides-Extra: docs
Requires-Dist: sphinx==3.0.1; extra == "docs"
Requires-Dist: sphinx-astropy; extra == "docs"
Requires-Dist: nbsphinx; extra == "docs"
Requires-Dist: nbconvert; extra == "docs"
Requires-Dist: nbformat; extra == "docs"
Requires-Dist: ipykernel; extra == "docs"
Dynamic: author
Dynamic: author-email
Dynamic: home-page
Dynamic: license-file
Dynamic: requires
Dynamic: summary
